wasc/__about__.py
wasc/__init__.py
wasc/__main__.py
wasc/abstract_checker.py
wasc/checker_factory.py
wasc/checkers.py
wasc/utils.py
wasc/cli/__init__.py
wasc-1.1.0.dist-info/METADATA
wasc-1.1.0.dist-info/WHEEL
wasc-1.1.0.dist-info/entry_points.txt
wasc-1.1.0.dist-info/licenses/LICENSE.txt
wasc-1.1.0.dist-info/RECORD
