Metadata-Version: 2.1
Name: wasc
Version: 1.1.0
Summary: Web Accessibility Simple Checker
Project-URL: Documentation, https://github.com/gcollet/wasc#readme
Project-URL: Issues, https://github.com/gcollet/wasc/issues
Project-URL: Source, https://github.com/gcollet/wasc
Author-email: Guillaume Collet <bilouweb@free.fr>, Juliette Francis <juliette.francis@etudiant.univ-rennes.fr>
License-Expression: CECILL-2.1
License-File: LICENSE.txt
Keywords: Accessibility,Checker,Criteria,Web
Classifier: Development Status :: 5 - Production/Stable
Classifier: Programming Language :: Python :: 3.12
Classifier: Programming Language :: Python :: Implementation :: CPython
Classifier: Programming Language :: Python :: Implementation :: PyPy
Requires-Python: >=3.7
Requires-Dist: beautifulsoup4
Requires-Dist: click
Requires-Dist: pandas
Requires-Dist: tqdm
Requires-Dist: trafilatura
